{
  "server": {
    "success": "با موفقیت انجام شد!",
    "backToHome": "بازگشت به صفحه اصلی",
    "viewServer": "مشاهده سرور",
    "failed": "انجام نشد",
    "failed1": "یه چیزی درست پیش نرفت! خطای مربوطه در کلیپبورد شما کپی شد، با کلیک کردن روی اینجا به سرور دیسکوردمان بپیوندید و این خطا را در support# برای ما بفرستید و ما شما را راهنمایی خواهیم کرد!",
    "tryAgain": "تلاش مجدد",
    "stepProgress": "مرحله { Step } از 3",
    "header": "افزودن یک سرور ماینکرافت جدید به کرفتی",
    "verification": "تائید هویت",
    "tellMore": "بیشتر به ما درباره { Name } بگویید",
    "serverName": "نام سرور",
    "serverIp": "آدرس IP سرور",
    "serverPort": "پورت سرور",
    "type": "نوع/پلتفرم",
    "ping": "پینگ کردن برای ادامه",
    "verificationMethod": "روش تأیید هویت",
    "motdInstructions": "در جایی در MOTD سرور خودتان این کد را شامل کنید تا مشخص شود که این سرور شماست و دسترسی مدیریت را برای افزودن آن دارید",
    "txtInstructions": "در تنظیمات DNS خود، یک فایل رکورد TXT در { Code } ایجاد کنید و در محتوای آن، کد زیر را در محتوای آن شامل کنید",
    "note": " لطفا این را درنظر داشته باشید که DNS مقداری طول می کشد تا خود را بروزرسانی کند، پس هر چند ثانیه یه بار چک کنید",
    "verified": "تایید شد",
    "tags": "تگ ها",
    "languages": "زبان(ها)",
    "maxLanguages": "حداکثر 3 زبان",
    "version": "نسخه",
    "short": "توضیح کوتاه",
    "long": "توضیح طولانی",
    "charsRemaining": "کاراکتر باقی مانده",
    "descLimit": "(حداکثر { Number } کاراکتر)",
    "website": "وبسایت",
    "previous": "قبلی",
    "next": "بعدی",
    "complete": "انجام شد",
    "errors": {
      "loggedIn": "شما باید وارد کرفتی شوید تا بتوانید سرور خود را اضافه کنید. از گوشه بالا سمت راست سایت وارد شوید.",
      "offline": "سرور شما آفلاین می باشد. مطمعن شوید که قبل از ثبت مجدد، آنلاین می شود."
    }
  }
}
