{
  "mcservers": "Сервера Minecraft",
  "servers": "Серверы",
  "searchServer": "Поиск конкретного сервера",
  "tags": "Теги",
  "sortBy": "Сортировать по",
  "orderBy": "Упорядочить по",
  "platform": "Платформа",
  "version": "Версия",
  "language": "Язык",
  "showOffline": "Показать оффлайн серверы",
  "playersOnline": "Онлайн",
  "upvotesMonthly": "Кол-во голосов (за месяц)",
  "upvotesLifetime": "Кол-во голосов (за все время)",
  "viewsMonthly": "Просмотров (за месяц)",
  "viewsLifetime": "Просмотров (за все время)",
  "uptime": "Время непрерывной работы",
  "recentlyListed": "Недавно добавлен в список",
  "highlow": "От высокой к низкой",
  "lowhigh": "От низкой к высокой",
  "primaryLanguage": "Язык (основной)",
  "copyip": "Скопировать IP",
  "clickTag": "Нажмите для просмотра серверов с этим тегом",
  "ipCopiedTop": "IP скопирован",
  "ipCopiedBot": "скопирован в буфер обмена!",
  "lastPing": "Обновлено",
  "website": "Сайт",
  "listedBy": "Размещен",
  "listedOn": "Добавлен",
  "lastEdit": "Последнее редактирование",
  "topUpvoters": "Топ голосов за {{Month}}"
}
