{
  "header": "Minecraft рд╕рд░реНрд╡рд░, рдЦрд┐рд▓рд╛рдбрд╝реА рдФрд░ рд╕реНрдХрд┐рди рдХреА рдЦреЛрдЬ рдХрд░реЗрдВ!",
  "subheader": "Minecraft рдЙрдкрдпреЛрдЧрдХрд░реНрддрд╛ рдирд╛рдо рдЦреЛрдЬреЗрдВ, рд╢реАрд░реНрд╖ рд╡реЛрдЯ рдХрд┐рдП рдЧрдП Minecraft рд╕рд░реНрд╡рд░, рдЕрджреНрд╡рд┐рддреАрдп рд╕реНрдХрд┐рди рдФрд░ рдЦрд┐рд▓рд╛рдбрд╝реА рдЖрдБрдХрдбрд╝реЗ рдЦреЛрдЬреЗрдВ! Minecraft рд╕рдореБрджрд╛рдп рджреНрд╡рд╛рд░рд╛, Minecraft рд╕рдореБрджрд╛рдп рдХреЗ рд▓рд┐рдП рдирд┐рд░реНрдорд┐рддред",
  "topServers": "{ Month } рдореЗрдВ рд╕рд░реНрд╡рд╛рдзрд┐рдХ рд╡реЛрдЯ рдХрд┐рдпреЗ рдЧрдП Minecraft Servers",
  "topPlayers": "{ Month } рдореЗрдВ рд╕рд░реНрд╡рд╛рдзрд┐рдХ рд╡реЛрдЯ рдХрд┐рдпреЗ рдЧрдП Minecraft Players",
  "topSkins": "{ Month } рдореЗрдВ рд╕рд░реНрд╡рд╛рдзрд┐рдХ рд╡реЛрдЯ рдХреА рдЧрдпреА Minecraft Skins",
  "mcnews": "Minecraft рдЦрдмрд░",
  "latestmcnews": "рдирд╡реАрдирддрдо Minecraft рдЦрдмрд░",
  "viewmore": "рдФрд░ рдЕрдзрд┐рдХ рджреЗрдЦреЗ",
  "explore": "рдЦреЛрдЬ рдХрд░реЗрдВ",
  "noResults": "рдХреЛрдИ рдкрд░рд┐рдгрд╛рдо рдирд╣реАрдВ рдорд┐рд▓рд╛",
  "results": "ЁЯФО рдпрд╣ рд░рд╣реА рдЖрдкрдХреА рдЦрдмрд░реЗрдВ",
  "january": "рдЬрдирд╡рд░реА",
  "february": "рдлрд╝рд░рд╡рд░реА",
  "march": "рдорд╛рд░реНрдЪ",
  "april": "рдЕрдкреНрд░реИрд▓",
  "may": "рдордИ",
  "june": "рдЬреВрди",
  "july": "рдЬреБрд▓рд╛рдИ",
  "august": "рдЕрдЧрд╕реНрдд",
  "september": "рд╕рд┐рддрдВрдмрд░",
  "october": "рдЕрдХреНрдЯреВрдмрд░",
  "November": "рдирд╡рдВрдмрд░",
  "December": "рджрд┐рд╕рдВрдмрд░",
  "footer": {
    "about": "рдмрд╛рд░реЗ рдореЗрдВ",
    "aboutus": "рд╣рдорд╛рд░реЗ рдмрд╛рд░реЗ рдореЗрдВ",
    "premium": "рдкреНрд░реАрдорд┐рдпрдо",
    "status": "рд╕реНрдерд┐рддрд┐",
    "navigation": "рдиреЗрд╡рд┐рдЧреЗрд╢рди",
    "feedback": "рдлреАрдбрдмреИрдХ",
    "legal": "рдХрд╛рдиреВрдиреА",
    "tos": "рд╕реЗрд╡рд╛ рдХреА рд╢рд░реНрддреЗрдВ",
    "privacy": "рдЧреЛрдкрдиреАрдпрддрд╛ рдиреАрддрд┐",
    "copyright": "┬й crafty.gg | Discord рдпрд╛ Mojang рд╕реЗ рд╕рдореНрдмрдВрдзрд┐рдд рдирд╣реАрдВ"
  },
  "reachedBedrock": "рдЖрдзрд╛рд░рд╢рд┐рд▓рд╛ рдкрд░ рдкрд╣реБрдБрдЪ рдЧрдпрд╛"
}
